drb/drivers/litto3d/__init__.py
drb/drivers/litto3d/_version.py
drb/drivers/litto3d/nodes.py
drb/topics/litto3d/__init__.py
drb/topics/litto3d/cortex.yml
drb_driver_litto3d-1.3.0.dist-info/METADATA
drb_driver_litto3d-1.3.0.dist-info/WHEEL
drb_driver_litto3d-1.3.0.dist-info/entry_points.txt
drb_driver_litto3d-1.3.0.dist-info/top_level.txt
drb_driver_litto3d-1.3.0.dist-info/RECORD
