Metadata-Version: 2.1
Name: drb-driver-litto3d
Version: 1.3.0
Summary: DRB Litto3D driver
Author: GAEL Systems
Author-email: drb-python@gael.fr
License: LGPLv3
Project-URL: Documentation, http://drb-python.gitlab.io/impl/litto3d
Project-URL: Source, https://gitlab.com/drb-python/impl/litto3d
Classifier: Programming Language :: Python :: 3.8
Classifier: Environment :: Plugins
Classifier: License :: OSI Approved :: GNU Lesser General Public License v3 (LGPLv3)
Requires-Python: >=3.8
Requires-Dist: drb ~=2.2.0
Requires-Dist: numpy >=1.21.2
Requires-Dist: pandas >=1.5.3
Requires-Dist: rasterio >=1.3.5
